setup.py
ava/__init__.py
ava/client/__init__.py
ava/client/api_cli.py
ava/env/__init__.py
ava/env/environment.py
ava/env/test_env.py
ava/evals/__init__.py
ava/evals/evals.py
ava/evals/metrics.py
ava/evals/test_metrics.py
ava/log/__init__.py
ava/log/logger.py
ava/monitor/__init__.py
ava/monitor/caffe.py
ava/monitor/common.py
ava/monitor/config.py
ava/monitor/mxnet.py
ava/monitor/test_monitor.py
ava/monitor/parser/__init__.py
ava/monitor/parser/caffe.py
ava/monitor/parser/caffe_raw.py
ava/monitor/parser/extract_seconds.py
ava/monitor/parser/stats.py
ava/monitor/probe/__init__.py
ava/monitor/probe/probe.py
ava/monitor/probe/protocol/__init__.py
ava/monitor/probe/protocol/encode.py
ava/monitor/probe/protocol/metric.py
ava/params/__init__.py
ava/params/params.py
ava/params/test_params.py
ava/tools/__init__.py
ava/tools/image_uploader.py
ava/train/__init__.py
ava/train/base.py
ava/train/worker/__init__.py
ava/train/worker/snapshot.py
ava/utils/__init__.py
ava/utils/cmd.py
ava/utils/compress.py
ava/utils/config.py
ava/utils/date.py
ava/utils/error.py
ava/utils/fetcher.py
ava/utils/fileloc.py
ava/utils/test_date.py
ava/utils/test_tool.py
ava/utils/test_utils.py
ava/utils/tool.py
ava/utils/uploader.py
ava/utils/utils.py
ava_sdk.egg-info/PKG-INFO
ava_sdk.egg-info/SOURCES.txt
ava_sdk.egg-info/dependency_links.txt
ava_sdk.egg-info/requires.txt
ava_sdk.egg-info/top_level.txt