Metadata-Version: 1.2
Name: ava-sdk
Version: 0.1.2
Summary: AVA Python SDK
Home-page: http://www.qiniu.com
Maintainer: Qiniu ATLab
Maintainer-email: ai@qiniu.com
License: UNKNOWN
Platform: UNKNOWN
